mcp_server_msnweather/__init__.py
mcp_server_msnweather/__main__.py
mcp_server_msnweather/server.py
mcp_server_msnweather-0.3.0.dist-info/METADATA
mcp_server_msnweather-0.3.0.dist-info/WHEEL
mcp_server_msnweather-0.3.0.dist-info/entry_points.txt
mcp_server_msnweather-0.3.0.dist-info/licenses/LICENSE
mcp_server_msnweather-0.3.0.dist-info/RECORD
