Metadata-Version: 2.4
Name: mcp-server-msnweather
Version: 0.3.0
Summary: MCP weather server using MSN Weather API
License-Expression: MIT
License-File: LICENSE
Requires-Python: >=3.10
Requires-Dist: httpx>=0.28.1
Requires-Dist: mcp[cli]>=1.2.0
